p2lz/__init__.py
p2lz/_version.py
p2lz/dynamodb.py
p2lz/tools.py
p2lz/tools_error.py
p2lz-0.1.3.dist-info/LICENSE.txt
p2lz-0.1.3.dist-info/METADATA
p2lz-0.1.3.dist-info/WHEEL
p2lz-0.1.3.dist-info/top_level.txt
p2lz-0.1.3.dist-info/RECORD
