Metadata-Version: 2.1
Name: p2lz
Version: 0.1.3
Summary: Private tools i.e. p2lz
Classifier: Programming Language :: Python :: 3.10
Requires-Python: >=3.10.0
License-File: LICENSE.txt
Requires-Dist: boto3 (>=1.26.129)
